monoprompt/__init__.py
monoprompt/monoprompt.py
monoprompt/version.py
monoprompt-1.0.1.dist-info/LICENSE
monoprompt-1.0.1.dist-info/METADATA
monoprompt-1.0.1.dist-info/WHEEL
monoprompt-1.0.1.dist-info/top_level.txt
monoprompt-1.0.1.dist-info/RECORD
