Metadata-Version: 2.1
Name: monoprompt
Version: 1.0.1
Summary: Decorate your command-line interface and simplify complex user input with an allowlist or blocklist.
Home-page: https://github.com/rmaniego/monoprompt
Author: Rodney Maniego Jr.
Author-email: rod.maniego23@gmail.com
License: MIT
Download-URL: https://github.com/rmaniego/monoprompt/archive/v1.0.tar.gz
Keywords: CONSOLE,COMMANDLINE,INPUT,UI
Platform: UNKNOWN
Classifier: Development Status :: 5 - Production/Stable
Classifier: Intended Audience :: Developers
Classifier: Topic :: Software Development :: Build Tools
Classifier: License :: OSI Approved :: MIT License
Classifier: Programming Language :: Python :: 3
Requires-Python: >=3.6
